KDOne/__init__.py
KDOne/api.py
KDOne/models/__init__.py
KDOne/models/complex.py
KDOne/models/device.py
KDOne/utils/__init__.py
KDOne/utils/encryption.py
KDOne-1.1.0.dist-info/LICENSE
KDOne-1.1.0.dist-info/METADATA
KDOne-1.1.0.dist-info/WHEEL
KDOne-1.1.0.dist-info/top_level.txt
KDOne-1.1.0.dist-info/RECORD
