Metadata-Version: 2.1
Name: KDOne
Version: 1.1.0
Summary: KDOne Navien Home Network API Wrapper
Home-page: https://github.com/soulee-dev/KDOne
Author: Soul Lee
Author-email: alus20x@gmail.com
Classifier: Programming Language :: Python :: 3
Classifier: License :: OSI Approved :: MIT License
Classifier: Operating System :: OS Independent
Requires-Python: >=3.6
License-File: LICENSE
Requires-Dist: certifi==2024.8.30
Requires-Dist: cffi==1.17.1
Requires-Dist: charset-normalizer==3.4.0
Requires-Dist: cryptography==43.0.3
Requires-Dist: idna==3.10
Requires-Dist: pycparser==2.22
Requires-Dist: requests==2.32.3
Requires-Dist: urllib3==2.2.3
